pycatapi/__init__.py
pycatapi/client.py
PyCatApi-1.0.6.dist-info/LICENSE
PyCatApi-1.0.6.dist-info/METADATA
PyCatApi-1.0.6.dist-info/WHEEL
PyCatApi-1.0.6.dist-info/top_level.txt
PyCatApi-1.0.6.dist-info/RECORD
