Metadata-Version: 2.1
Name: PyCatApi
Version: 1.0.6
Summary: A Python wrapper for TheCatApi
Home-page: https://github.com/TheFarGG/pycatapi/
Author: TheFarGG
License: MIT
Platform: UNKNOWN
Classifier: License :: OSI Approved :: MIT License
Classifier: Programming Language :: Python :: 3
Classifier: Programming Language :: Python :: 3.9
Requires-Python: >=3.8.0
Requires-Dist: requests
